emoc/.DS_Store
emoc/__init__.py
emoc/__pycache__/__init__.cpython-39.pyc
emoc/algorithm/.DS_Store
emoc/algorithm/__init__.py
emoc/algorithm/algorithm.py
emoc/algorithm/nsga2_framework.py
emoc/algorithm/__pycache__/__init__.cpython-37.pyc
emoc/algorithm/__pycache__/__init__.cpython-39.pyc
emoc/algorithm/__pycache__/algorithm.cpython-37.pyc
emoc/algorithm/__pycache__/algorithm.cpython-39.pyc
emoc/algorithm/__pycache__/cmoead.cpython-37.pyc
emoc/algorithm/__pycache__/cmoead.cpython-39.pyc
emoc/algorithm/__pycache__/nsga2.cpython-37.pyc
emoc/algorithm/__pycache__/nsga2.cpython-39.pyc
emoc/algorithm/__pycache__/nsga2_framework.cpython-37.pyc
emoc/algorithm/__pycache__/nsga2_framework.cpython-39.pyc
emoc/algorithm/__pycache__/parego.cpython-37.pyc
emoc/algorithm/__pycache__/parego.cpython-39.pyc
emoc/algorithm/moo/__init__.py
emoc/algorithm/moo/cmoead.py
emoc/algorithm/moo/nsga2.py
emoc/algorithm/moo/parego.py
emoc/algorithm/moo/__pycache__/cmoead.cpython-37.pyc
emoc/algorithm/moo/__pycache__/cmoead.cpython-39.pyc
emoc/algorithm/moo/__pycache__/nsga2.cpython-37.pyc
emoc/algorithm/moo/__pycache__/nsga2.cpython-39.pyc
emoc/algorithm/moo/__pycache__/parego.cpython-37.pyc
emoc/algorithm/moo/__pycache__/parego.cpython-39.pyc
emoc/algorithms/__init__.py
emoc/algorithms/algorithm.py
emoc/algorithms/nsga2_framework.py
emoc/core/__init__.py
emoc/core/constants.py
emoc/core/emoc_manager.py
emoc/core/global_information.py
emoc/core/individual.py
emoc/core/weighted_gpmodel.py
emoc/core/__pycache__/__init__.cpython-37.pyc
emoc/core/__pycache__/__init__.cpython-39.pyc
emoc/core/__pycache__/constants.cpython-37.pyc
emoc/core/__pycache__/constants.cpython-39.pyc
emoc/core/__pycache__/emoc_manager.cpython-37.pyc
emoc/core/__pycache__/emoc_manager.cpython-39.pyc
emoc/core/__pycache__/global_information.cpython-37.pyc
emoc/core/__pycache__/global_information.cpython-39.pyc
emoc/core/__pycache__/individual.cpython-37.pyc
emoc/core/__pycache__/individual.cpython-39.pyc
emoc-0.0.1a1.dist-info/METADATA
emoc-0.0.1a1.dist-info/WHEEL
emoc-0.0.1a1.dist-info/top_level.txt
emoc-0.0.1a1.dist-info/RECORD
